Workbook

Sheet dimDate
A1: Date | B1: Calendar Year | C1: Month Name | D1: Month Number | E1: Weekday | F1: Weekday number | G1: Quarter | H1: Month Sort | I1: Month Year | J1: MonthOffset | K1: Quarter Number | L1: Quarter Year | M1: Quarter Start Date | N1: Quarter Sort | O1: QuarterOffset
A2: 46002 | B2: 2025 | C2: December | D2: 12 | E2: Thursday | F2: 5 | G2: Q4 | H2: 24312 | I2: 45992 | J2: 7 | K2: 4 | L2: 2025 Q4 | M2: 45931 | N2: 8104 | O2: 3
A3: 46001 | B3: 2025 | C3: December | D3: 12 | E3: Wednesday | F3: 4 | G3: Q4 | H3: 24312 | I3: 45992 | J3: 7 | K3: 4 | L3: 2025 Q4 | M3: 45931 | N3: 8104 | O3: 3
A4: 46000 | B4: 2025 | C4: December | D4: 12 | E4: Tuesday | F4: 3 | G4: Q4 | H4: 24312 | I4: 45992 | J4: 7 | K4: 4 | L4: 2025 Q4 | M4: 45931 | N4: 8104 | O4: 3
A5: 45999 | B5: 2025 | C5: December | D5: 12 | E5: Monday | F5: 2 | G5: Q4 | H5: 24312 | I5: 45992 | J5: 7 | K5: 4 | L5: 2025 Q4 | M5: 45931 | N5: 8104 | O5: 3
A6: 45998 | B6: 2025 | C6: December | D6: 12 | E6: Sunday | F6: 1 | G6: Q4 | H6: 24312 | I6: 45992 | J6: 7 | K6: 4 | L6: 2025 Q4 | M6: 45931 | N6: 8104 | O6: 3
A7: 45997 | B7: 2025 | C7: December | D7: 12 | E7: Saturday | F7: 7 | G7: Q4 | H7: 24312 | I7: 45992 | J7: 7 | K7: 4 | L7: 2025 Q4 | M7: 45931 | N7: 8104 | O7: 3
A8: 45996 | B8: 2025 | C8: December | D8: 12 | E8: Friday | F8: 6 | G8: Q4 | H8: 24312 | I8: 45992 | J8: 7 | K8: 4 | L8: 2025 Q4 | M8: 45931 | N8: 8104 | O8: 3
A9: 45995 | B9: 2025 | C9: December | D9: 12 | E9: Thursday | F9: 5 | G9: Q4 | H9: 24312 | I9: 45992 | J9: 7 | K9: 4 | L9: 2025 Q4 | M9: 45931 | N9: 8104 | O9: 3
A10: 45994 | B10: 2025 | C10: December | D10: 12 | E10: Wednesday | F10: 4 | G10: Q4 | H10: 24312 | I10: 45992 | J10: 7 | K10: 4 | L10: 2025 Q4 | M10: 45931 | N10: 8104 | O10: 3
A11: 45993 | B11: 2025 | C11: December | D11: 12 | E11: Tuesday | F11: 3 | G11: Q4 | H11: 24312 | I11: 45992 | J11: 7 | K11: 4 | L11: 2025 Q4 | M11: 45931 | N11: 8104 | O11: 3
A12: 45992 | B12: 2025 | C12: December | D12: 12 | E12: Monday | F12: 2 | G12: Q4 | H12: 24312 | I12: 45992 | J12: 7 | K12: 4 | L12: 2025 Q4 | M12: 45931 | N12: 8104 | O12: 3
A13: 45991 | B13: 2025 | C13: November | D13: 11 | E13: Sunday | F13: 1 | G13: Q4 | H13: 24311 | I13: 45962 | J13: 8 | K13: 4 | L13: 2025 Q4 | M13: 45931 | N13: 8104 | O13: 3
... A101: 45903 | B101: 2025 | C101: September | D101: 9 | E101: Wednesday | F101: 4 | G101: Q3 | H101: 24309 | I101: 45901 | J101: 10 | K101: 3 | L101: 2025 Q3 | M101: 45839 | N101: 8103 | O101: 4

Sheet Activity Codes
A1: CODE | B1: REPORTING CATEGORY | C1: ACTIVITY CODE NAME
A2: 002 | B2: Basic Career Service (Self-Service) | C2: Self-Service AJCC Employment and Workforce Information Service
A3: 004 | B3: Basic Career Service (Self-Service) | C3: Self-Service Information on Training Providers/Performance Outcomes
A4: 005 | B4: Basic Career Service (Self-Service) | C4: Self-Service Labor Market Research
A5: 006 | B5: Basic Career Service (Self-Service) | C5: Self-Service Job Search through CalJOBS
A6: 06M | B6: Basic Career Service (Self-Service) | C6: Self-Service Job Search through Mobile App
A7: 007 | B7: Basic Career Service (Self-Service) | C7: Self-Service Initial Resume
A8: 008 | B8: Basic Career Service (Self-Service) | C8: Self-Service Resume: Update and Additions
A9: 010 | B9: Housekeeping | C9: Tracking Co-funded Services
A10: 050 | B10: Basic Career Service (Self-Service) | C10: Information on DI or PFL
A11: 051 | B11: Basic Career Service (Self-Service) | C11: Information on Social Services Programs
A12: 052 | B12: Basic Career Service (Self-Service) | C12: Information on other Public Assistance Programs
... A255: F22 | B255: Follow-up | C255: Supportive Service: Postsecondary Educational Materials

Sheet Participants
A1: EXIT DATE | B1: LWDB | C1: RESPONSIBLE OFFICE | D1: PARTICIPATION DATE | E1: GRANT ENROLL DATE | F1: LAST GRANT ACTIVITY DATE | G1: PROJECTED GRANT ACTIVITY END DATE | H1: RECEIVED CREDENTIAL | I1: ENTERED EMPLOYMENT | J1: WITH DISABILITY | K1: APP ID
B2: 29 | C2: =IFERROR(INDEX(Regions!$A$2:$A$19,MATCH(B2,Regions!$B$2:$B$19,0))&" Workforce Center","") -> Grand Meadow Workforce Center | D2: 46233 | E2: 46233 | F2: 46233 | G2: 46233 | H2: N | I2: N | J2: Y | K2: 1
B3: 12 | C3: =IFERROR(INDEX(Regions!$A$2:$A$19,MATCH(B3,Regions!$B$2:$B$19,0))&" Workforce Center","") -> Lakebridge Workforce Center | D3: 46233 | E3: 46233 | F3: 46233 | G3: 46233 | H3: N | I3: N | J3: Y | K3: 6
B4: 20 | C4: =IFERROR(INDEX(Regions!$A$2:$A$19,MATCH(B4,Regions!$B$2:$B$19,0))&" Workforce Center","") -> Rivermoor Workforce Center | D4: 46233 | E4: 46233 | F4: 46233 | G4: 46233 | H4: N | I4: N | J4: Y | K4: 1
B5: 43 | C5: =IFERROR(INDEX(Regions!$A$2:$A$19,MATCH(B5,Regions!$B$2:$B$19,0))&" Workforce Center","") -> Stonefield Workforce Center | D5: 46225 | E5: 46233 | F5: 46233 | G5: 46233 | H5: N | I5: N | J5: Y | K5: 1
B6: 29 | C6: =IFERROR(INDEX(Regions!$A$2:$A$19,MATCH(B6,Regions!$B$2:$B$19,0))&" Workforce Center","") -> Grand Meadow Workforce Center | D6: 46232 | E6: 46233 | F6: 46233 | G6: 46233 | H6: N | I6: N | J6: N | K6: 1
B7: 8 | C7: =IFERROR(INDEX(Regions!$A$2:$A$19,MATCH(B7,Regions!$B$2:$B$19,0))&" Workforce Center","") -> Amberfield Workforce Center | D7: 46232 | E7: 46232 | F7: 46232 | G7: 46232 | H7: N | I7: N | J7: N | K7: 1
B8: 32 | C8: =IFERROR(INDEX(Regions!$A$2:$A$19,MATCH(B8,Regions!$B$2:$B$19,0))&" Workforce Center","") -> Silver Creek Workforce Center | D8: 45978 | E8: 46230 | F8: 46230 | G8: 46230 | H8: N | I8: N | J8: N | K8: 1
B9: 33 | C9: =IFERROR(INDEX(Regions!$A$2:$A$19,MATCH(B9,Regions!$B$2:$B$19,0))&" Workforce Center","") -> Redstone Workforce Center | D9: 46227 | E9: 46227 | F9: 46227 | G9: 46227 | H9: N | I9: N | J9: Y | K9: 1
B10: 8 | C10: =IFERROR(INDEX(Regions!$A$2:$A$19,MATCH(B10,Regions!$B$2:$B$19,0))&" Workforce Center","") -> Amberfield Workforce Center | D10: 46226 | E10: 46226 | F10: 46232 | G10: 46232 | H10: N | I10: N | J10: N | K10: 1
B11: 12 | C11: =IFERROR(INDEX(Regions!$A$2:$A$19,MATCH(B11,Regions!$B$2:$B$19,0))&" Workforce Center","") -> Lakebridge Workforce Center | D11: 46226 | E11: 46226 | F11: 46226 | G11: 46226 | H11: N | I11: N | J11: Y | K11: 4
B12: 22 | C12: =IFERROR(INDEX(Regions!$A$2:$A$19,MATCH(B12,Regions!$B$2:$B$19,0))&" Workforce Center","") -> Pine Hollow Workforce Center | D12: 46226 | E12: 46226 | F12: 46226 | G12: 46226 | H12: N | I12: N | J12: Y | K12: 1
B13: 20 | C13: =IFERROR(INDEX(Regions!$A$2:$A$19,MATCH(B13,Regions!$B$2:$B$19,0))&" Workforce Center","") -> Rivermoor Workforce Center | D13: 46164 | E13: 46225 | F13: 46225 | G13: 46225 | H13: N | I13: N | J13: Y | K13: 1
B14: 29 | C14: =IFERROR(INDEX(Regions!$A$2:$A$19,MATCH(B14,Regions!$B$2:$B$19,0))&" Workforce Center","") -> Grand Meadow Workforce Center | D14: 46223 | E14: 46225 | F14: 46225 | G14: 46225 | H14: N | I14: N | J14: Y | K14: 1
B15: 8 | C15: =IFERROR(INDEX(Regions!$A$2:$A$19,MATCH(B15,Regions!$B$2:$B$19,0))&" Workforce Center","") -> Amberfield Workforce Center | D15: 46205 | E15: 46224 | G15: 46598 | H15: N | I15: N | J15: Y | K15: 1
B16: 48 | C16: =IFERROR(INDEX(Regions!$A$2:$A$19,MATCH(B16,Regions!$B$2:$B$19,0))&" Workforce Center","") -> Westhaven Workforce Center | D16: 46223 | E16: 46223 | F16: 46223 | G16: 46223 | H16: N | I16: N | J16: Y | K16: 1
B17: 42 | C17: =IFERROR(INDEX(Regions!$A$2:$A$19,MATCH(B17,Regions!$B$2:$B$19,0))&" Workforce Center","") -> Willow Bend Workforce Center | D17: 46209 | E17: 46220 | F17: 46220 | G17: 46220 | H17: N | I17: N | J17: Y | K17: 1
B18: 35 | C18: =IFERROR(INDEX(Regions!$A$2:$A$19,MATCH(B18,Regions!$B$2:$B$19,0))&" Workforce Center","") -> Elm Harbor Workforce Center | D18: 46220 | E18: 46220 | F18: 46220 | G18: 46220 | H18: N | I18: N | J18: Y | K18: 1
B19: 35 | C19: =IFERROR(INDEX(Regions!$A$2:$A$19,MATCH(B19,Regions!$B$2:$B$19,0))&" Workforce Center","") -> Elm Harbor Workforce Center | D19: 46219 | E19: 46219 | F19: 46219 | G19: 46219 | H19: N | I19: N | J19: Y | K19: 1
B20: 29 | C20: =IFERROR(INDEX(Regions!$A$2:$A$19,MATCH(B20,Regions!$B$2:$B$19,0))&" Workforce Center","") -> Grand Meadow Workforce Center | D20: 46218 | E20: 46219 | F20: 46219 | G20: 46219 | H20: N | I20: N | J20: Y | K20: 1
B21: 33 | C21: =IFERROR(INDEX(Regions!$A$2:$A$19,MATCH(B21,Regions!$B$2:$B$19,0))&" Workforce Center","") -> Redstone Workforce Center | D21: 46219 | E21: 46219 | G21: 46255 | H21: N | I21: N | J21: Y | K21: 1
B22: 33 | C22: =IFERROR(INDEX(Regions!$A$2:$A$19,MATCH(B22,Regions!$B$2:$B$19,0))&" Workforce Center","") -> Redstone Workforce Center | D22: 46219 | E22: 46219 | F22: 46230 | G22: 46230 | H22: N | I22: N | J22: Y | K22: 1
B23: 8 | C23: =IFERROR(INDEX(Regions!$A$2:$A$19,MATCH(B23,Regions!$B$2:$B$19,0))&" Workforce Center","") -> Amberfield Workforce Center | D23: 46218 | E23: 46218 | F23: 46218 | G23: 46218 | H23: N | I23: N | J23: Y | K23: 1
B24: 28 | C24: =IFERROR(INDEX(Regions!$A$2:$A$19,MATCH(B24,Regions!$B$2:$B$19,0))&" Workforce Center","") -> Clearfork Workforce Center | D24: 46216 | E24: 46218 | F24: 46218 | G24: 46218 | H24: N | I24: N | J24: Y | K24: 1
B25: 22 | C25: =IFERROR(INDEX(Regions!$A$2:$A$19,MATCH(B25,Regions!$B$2:$B$19,0))&" Workforce Center","") -> Pine Hollow Workforce Center | D25: 46217 | E25: 46217 | F25: 46217 | G25: 46217 | H25: N | I25: N | J25: Y | K25: 1
B26: 42 | C26: =IFERROR(INDEX(Regions!$A$2:$A$19,MATCH(B26,Regions!$B$2:$B$19,0))&" Workforce Center","") -> Willow Bend Workforce Center | D26: 46209 | E26: 46217 | F26: 46217 | G26: 46217 | H26: N | I26: N | J26: Y | K26: 1
B27: 8 | C27: =IFERROR(INDEX(Regions!$A$2:$A$19,MATCH(B27,Regions!$B$2:$B$19,0))&" Workforce Center","") -> Amberfield Workforce Center | D27: 46176 | E27: 46217 | F27: 46231 | G27: 46231 | H27: N | I27: N | J27: Y | K27: 1
B28: 15 | C28: =IFERROR(INDEX(Regions!$A$2:$A$19,MATCH(B28,Regions!$B$2:$B$19,0))&" Workforce Center","") -> Maple Crossing Workforce Center | D28: 45369 | E28: 46217 | F28: 46217 | G28: 46217 | H28: N | I28: N | J28: Y | K28: 1
B29: 33 | C29: =IFERROR(INDEX(Regions!$A$2:$A$19,MATCH(B29,Regions!$B$2:$B$19,0))&" Workforce Center","") -> Redstone Workforce Center | D29: 46171 | E29: 46217 | F29: 46217 | G29: 46217 | H29: N | I29: N | J29: Y | K29: 1
B30: 33 | C30: =IFERROR(INDEX(Regions!$A$2:$A$19,MATCH(B30,Regions!$B$2:$B$19,0))&" Workforce Center","") -> Redstone Workforce Center | D30: 46213 | E30: 46216 | F30: 46217 | G30: 46217 | H30: N | I30: N | J30: Y | K30: 1
B31: 7 | C31: =IFERROR(INDEX(Regions!$A$2:$A$19,MATCH(B31,Regions!$B$2:$B$19,0))&" Workforce Center","") -> Prairie Glen Workforce Center | D31: 46216 | E31: 46216 | F31: 46227 | G31: 46227 | H31: N | I31: N | J31: Y | K31: 1
B32: 12 | C32: =IFERROR(INDEX(Regions!$A$2:$A$19,MATCH(B32,Regions!$B$2:$B$19,0))&" Workforce Center","") -> Lakebridge Workforce Center | D32: 46051 | E32: 46216 | F32: 46216 | G32: 46216 | H32: N | I32: N | J32: Y | K32: 1
B33: 45 | C33: =IFERROR(INDEX(Regions!$A$2:$A$19,MATCH(B33,Regions!$B$2:$B$19,0))&" Workforce Center","") -> Briar Lake Workforce Center | D33: 46216 | E33: 46216 | F33: 46216 | G33: 46216 | H33: N | I33: N | J33: Y | K33: 6
... B54: 33 | C54: =IFERROR(INDEX(Regions!$A$2:$A$19,MATCH(B54,Regions!$B$2:$B$19,0))&" Workforce Center","") -> Redstone Workforce Center | D54: 46205 | E54: 46205 | F54: 46205 | G54: 46205 | H54: N | I54: N | J54: Y | K54: 1
B55: 23 | C55: =IFERROR(INDEX(Regions!$A$2:$A$19,MATCH(B55,Regions!$B$2:$B$19,0))&" Workforce Center","") -> Oakmere Workforce Center | D55: 46204 | E55: 46204 | G55: 46477 | H55: N | I55: N | J55: Y | K55: 2
B56: 22 | C56: =IFERROR(INDEX(Regions!$A$2:$A$19,MATCH(B56,Regions!$B$2:$B$19,0))&" Workforce Center","") -> Pine Hollow Workforce Center | D56: 46204 | E56: 46204 | F56: 46217 | G56: 46217 | H56: N | I56: N | J56: N | K56: 1
B57: 33 | C57: =IFERROR(INDEX(Regions!$A$2:$A$19,MATCH(B57,Regions!$B$2:$B$19,0))&" Workforce Center","") -> Redstone Workforce Center | D57: 45953 | E57: 46204 | F57: 46204 | G57: 46204 | H57: N | I57: N | J57: Y | K57: 1
B58: 35 | C58: =IFERROR(INDEX(Regions!$A$2:$A$19,MATCH(B58,Regions!$B$2:$B$19,0))&" Workforce Center","") -> Elm Harbor Workforce Center | D58: 46204 | E58: 46204 | F58: 46204 | G58: 46204 | H58: N | I58: N | J58: Y | K58: 1
B59: 35 | C59: =IFERROR(INDEX(Regions!$A$2:$A$19,MATCH(B59,Regions!$B$2:$B$19,0))&" Workforce Center","") -> Elm Harbor Workforce Center | D59: 46120 | E59: 46204 | F59: 46204 | G59: 46204 | H59: N | I59: N | J59: Y | K59: 1
B60: 35 | C60: =IFERROR(INDEX(Regions!$A$2:$A$19,MATCH(B60,Regions!$B$2:$B$19,0))&" Workforce Center","") -> Elm Harbor Workforce Center | D60: 46132 | E60: 46204 | F60: 46204 | G60: 46204 | H60: N | I60: N | J60: Y | K60: 1
B61: 35 | C61: =IFERROR(INDEX(Regions!$A$2:$A$19,MATCH(B61,Regions!$B$2:$B$19,0))&" Workforce Center","") -> Elm Harbor Workforce Center | D61: 46203 | E61: 46203 | F61: 46203 | G61: 46203 | H61: N | I61: N | J61: Y | K61: 1
B62: 33 | C62: =IFERROR(INDEX(Regions!$A$2:$A$19,MATCH(B62,Regions!$B$2:$B$19,0))&" Workforce Center","") -> Redstone Workforce Center | D62: 46202 | E62: 46202 | F62: 46202 | G62: 46202 | H62: N | I62: Y | J62: Y | K62: 1
B63: 42 | C63: =IFERROR(INDEX(Regions!$A$2:$A$19,MATCH(B63,Regions!$B$2:$B$19,0))&" Workforce Center","") -> Willow Bend Workforce Center | D63: 46190 | E63: 46202 | F63: 46202 | G63: 46202 | H63: N | I63: N | J63: Y | K63: 1
B64: 7 | C64: =IFERROR(INDEX(Regions!$A$2:$A$19,MATCH(B64,Regions!$B$2:$B$19,0))&" Workforce Center","") -> Prairie Glen Workforce Center | D64: 46202 | E64: 46202 | F64: 46210 | G64: 46210 | H64: N | I64: N | J64: Y | K64: 1
B65: 7 | C65: =IFERROR(INDEX(Regions!$A$2:$A$19,MATCH(B65,Regions!$B$2:$B$19,0))&" Workforce Center","") -> Prairie Glen Workforce Center | D65: 46202 | E65: 46202 | F65: 46213 | G65: 46213 | H65: N | I65: Y | J65: Y | K65: 1
B66: 42 | C66: =IFERROR(INDEX(Regions!$A$2:$A$19,MATCH(B66,Regions!$B$2:$B$19,0))&" Workforce Center","") -> Willow Bend Workforce Center | D66: 46183 | E66: 46198 | F66: 46198 | G66: 46198 | H66: N | I66: N | J66: Y | K66: 1
B67: 20 | C67: =IFERROR(INDEX(Regions!$A$2:$A$19,MATCH(B67,Regions!$B$2:$B$19,0))&" Workforce Center","") -> Rivermoor Workforce Center | D67: 46185 | E67: 46197 | F67: 46197 | G67: 46197 | H67: N | I67: N | J67: Y | K67: 1
... B76: 42 | C76: =IFERROR(INDEX(Regions!$A$2:$A$19,MATCH(B76,Regions!$B$2:$B$19,0))&" Workforce Center","") -> Willow Bend Workforce Center | D76: 46182 | E76: 46191 | F76: 46191 | G76: 46191 | H76: N | I76: N | J76: Y | K76: 1
B77: 8 | C77: =IFERROR(INDEX(Regions!$A$2:$A$19,MATCH(B77,Regions!$B$2:$B$19,0))&" Workforce Center","") -> Amberfield Workforce Center | D77: 46191 | E77: 46191 | G77: 46598 | H77: N | I77: N | J77: N | K77: 1
B78: 7 | C78: =IFERROR(INDEX(Regions!$A$2:$A$19,MATCH(B78,Regions!$B$2:$B$19,0))&" Workforce Center","") -> Prairie Glen Workforce Center | D78: 46191 | E78: 46191 | F78: 46195 | G78: 46195 | H78: N | I78: N | J78: Y | K78: 1
B79: 35 | C79: =IFERROR(INDEX(Regions!$A$2:$A$19,MATCH(B79,Regions!$B$2:$B$19,0))&" Workforce Center","") -> Elm Harbor Workforce Center | D79: 46191 | E79: 46191 | F79: 46210 | G79: 46210 | H79: N | I79: N | J79: Y | K79: 1
B80: 22 | C80: =IFERROR(INDEX(Regions!$A$2:$A$19,MATCH(B80,Regions!$B$2:$B$19,0))&" Workforce Center","") -> Pine Hollow Workforce Center | D80: 46191 | E80: 46191 | F80: 46224 | G80: 46224 | H80: N | I80: N | J80: Y | K80: 1
B81: 22 | C81: =IFERROR(INDEX(Regions!$A$2:$A$19,MATCH(B81,Regions!$B$2:$B$19,0))&" Workforce Center","") -> Pine Hollow Workforce Center | D81: 46191 | E81: 46191 | F81: 46216 | G81: 46216 | H81: N | I81: N | J81: Y | K81: 1
B82: 33 | C82: =IFERROR(INDEX(Regions!$A$2:$A$19,MATCH(B82,Regions!$B$2:$B$19,0))&" Workforce Center","") -> Redstone Workforce Center | D82: 46191 | E82: 46191 | F82: 46203 | G82: 46203 | H82: N | I82: N | J82: Y | K82: 1
B83: 28 | C83: =IFERROR(INDEX(Regions!$A$2:$A$19,MATCH(B83,Regions!$B$2:$B$19,0))&" Workforce Center","") -> Clearfork Workforce Center | D83: 46191 | E83: 46191 | F83: 46205 | G83: 46205 | H83: N | I83: N | J83: Y | K83: 1
B84: 22 | C84: =IFERROR(INDEX(Regions!$A$2:$A$19,MATCH(B84,Regions!$B$2:$B$19,0))&" Workforce Center","") -> Pine Hollow Workforce Center | D84: 46189 | E84: 46189 | F84: 46218 | G84: 46218 | H84: N | I84: Y | J84: N | K84: 1
B85: 33 | C85: =IFERROR(INDEX(Regions!$A$2:$A$19,MATCH(B85,Regions!$B$2:$B$19,0))&" Workforce Center","") -> Redstone Workforce Center | D85: 46189 | E85: 46189 | F85: 46189 | G85: 46189 | H85: N | I85: N | J85: Y | K85: 1
B86: 12 | C86: =IFERROR(INDEX(Regions!$A$2:$A$19,MATCH(B86,Regions!$B$2:$B$19,0))&" Workforce Center","") -> Lakebridge Workforce Center | D86: 46181 | E86: 46189 | F86: 46196 | G86: 46196 | H86: N | I86: N | J86: Y | K86: 1
B87: 29 | C87: =IFERROR(INDEX(Regions!$A$2:$A$19,MATCH(B87,Regions!$B$2:$B$19,0))&" Workforce Center","") -> Grand Meadow Workforce Center | D87: 46189 | E87: 46189 | F87: 46216 | G87: 46216 | H87: N | I87: N | J87: Y | K87: 1
B88: 8 | C88: =IFERROR(INDEX(Regions!$A$2:$A$19,MATCH(B88,Regions!$B$2:$B$19,0))&" Workforce Center","") -> Amberfield Workforce Center | D88: 46189 | E88: 46189 | G88: 46600 | H88: N | I88: N | J88: Y | K88: 1
B89: 12 | C89: =IFERROR(INDEX(Regions!$A$2:$A$19,MATCH(B89,Regions!$B$2:$B$19,0))&" Workforce Center","") -> Lakebridge Workforce Center | D89: 46189 | E89: 46189 | F89: 46189 | G89: 46189 | H89: N | I89: N | J89: Y | K89: 12
B90: 48 | C90: =IFERROR(INDEX(Regions!$A$2:$A$19,MATCH(B90,Regions!$B$2:$B$19,0))&" Workforce Center","") -> Westhaven Workforce Center | D90: 46189 | E90: 46189 | F90: 46220 | G90: 46220 | H90: N | I90: N | J90: Y | K90: 2
B91: 42 | C91: =IFERROR(INDEX(Regions!$A$2:$A$19,MATCH(B91,Regions!$B$2:$B$19,0))&" Workforce Center","") -> Willow Bend Workforce Center | D91: 46182 | E91: 46188 | F91: 46188 | G91: 46188 | H91: N | I91: N | J91: Y | K91: 2
B92: 33 | C92: =IFERROR(INDEX(Regions!$A$2:$A$19,MATCH(B92,Regions!$B$2:$B$19,0))&" Workforce Center","") -> Redstone Workforce Center | D92: 46106 | E92: 46188 | F92: 46188 | G92: 46188 | H92: N | I92: N | J92: Y | K92: 1
B93: 20 | C93: =IFERROR(INDEX(Regions!$A$2:$A$19,MATCH(B93,Regions!$B$2:$B$19,0))&" Workforce Center","") -> Rivermoor Workforce Center | D93: 46188 | E93: 46188 | F93: 46226 | G93: 46226 | H93: N | I93: N | J93: Y | K93: 1
B94: 23 | C94: =IFERROR(INDEX(Regions!$A$2:$A$19,MATCH(B94,Regions!$B$2:$B$19,0))&" Workforce Center","") -> Oakmere Workforce Center | D94: 46188 | E94: 46188 | F94: 46188 | G94: 46188 | H94: N | I94: N | J94: Y | K94: 1
B95: 22 | C95: =IFERROR(INDEX(Regions!$A$2:$A$19,MATCH(B95,Regions!$B$2:$B$19,0))&" Workforce Center","") -> Pine Hollow Workforce Center | D95: 46188 | E95: 46188 | G95: 46387 | H95: N | I95: N | J95: Y | K95: 1
B96: 12 | C96: =IFERROR(INDEX(Regions!$A$2:$A$19,MATCH(B96,Regions!$B$2:$B$19,0))&" Workforce Center","") -> Lakebridge Workforce Center | D96: 46185 | E96: 46185 | F96: 46216 | G96: 46216 | H96: N | I96: N | J96: Y | K96: 1
B97: 23 | C97: =IFERROR(INDEX(Regions!$A$2:$A$19,MATCH(B97,Regions!$B$2:$B$19,0))&" Workforce Center","") -> Oakmere Workforce Center | D97: 45275 | E97: 46185 | F97: 46185 | G97: 46185 | H97: Y | I97: N | J97: Y | K97: 1
B98: 42 | C98: =IFERROR(INDEX(Regions!$A$2:$A$19,MATCH(B98,Regions!$B$2:$B$19,0))&" Workforce Center","") -> Willow Bend Workforce Center | D98: 46176 | E98: 46185 | F98: 46185 | G98: 46185 | H98: N | I98: N | J98: Y | K98: 1
B99: 42 | C99: =IFERROR(INDEX(Regions!$A$2:$A$19,MATCH(B99,Regions!$B$2:$B$19,0))&" Workforce Center","") -> Willow Bend Workforce Center | D99: 46176 | E99: 46184 | F99: 46184 | G99: 46184 | H99: N | I99: N | J99: Y | K99: 1
B100: 7 | C100: =IFERROR(INDEX(Regions!$A$2:$A$19,MATCH(B100,Regions!$B$2:$B$19,0))&" Workforce Center","") -> Prairie Glen Workforce Center | D100: 46184 | E100: 46184 | F100: 46230 | G100: 46230 | H100: N | I100: Y | J100: Y | K100: 1
B101: 20 | C101: =IFERROR(INDEX(Regions!$A$2:$A$19,MATCH(B101,Regions!$B$2:$B$19,0))&" Workforce Center","") -> Rivermoor Workforce Center | D101: 46113 | E101: 46183 | F101: 46227 | G101: 46227 | H101: N | I101: N | J101: Y | K101: 1
B102: 28 | C102: =IFERROR(INDEX(Regions!$A$2:$A$19,MATCH(B102,Regions!$B$2:$B$19,0))&" Workforce Center","") -> Clearfork Workforce Center | D102: 46183 | E102: 46183 | F102: 46234 | G102: 46234 | H102: Y | I102: N | J102: Y | K102: 1
B103: 42 | C103: =IFERROR(INDEX(Regions!$A$2:$A$19,MATCH(B103,Regions!$B$2:$B$19,0))&" Workforce Center","") -> Willow Bend Workforce Center | D103: 46176 | E103: 46182 | F103: 46182 | G103: 46182 | H103: N | I103: N | J103: Y | K103: 1
B104: 33 | C104: =IFERROR(INDEX(Regions!$A$2:$A$19,MATCH(B104,Regions!$B$2:$B$19,0))&" Workforce Center","") -> Redstone Workforce Center | D104: 46168 | E104: 46182 | F104: 46182 | G104: 46182 | H104: N | I104: N | J104: Y | K104: 1
B105: 42 | C105: =IFERROR(INDEX(Regions!$A$2:$A$19,MATCH(B105,Regions!$B$2:$B$19,0))&" Workforce Center","") -> Willow Bend Workforce Center | D105: 46105 | E105: 46182 | G105: 46360 | H105: N | I105: N | J105: Y | K105: 1
B106: 48 | C106: =IFERROR(INDEX(Regions!$A$2:$A$19,MATCH(B106,Regions!$B$2:$B$19,0))&" Workforce Center","") -> Westhaven Workforce Center | D106: 46181 | E106: 46181 | F106: 46220 | G106: 46220 | H106: N | I106: N | J106: Y | K106: 1
B107: 43 | C107: =IFERROR(INDEX(Regions!$A$2:$A$19,MATCH(B107,Regions!$B$2:$B$19,0))&" Workforce Center","") -> Stonefield Workforce Center | D107: 46181 | E107: 46181 | F107: 46181 | G107: 46181 | H107: N | I107: N | J107: Y | K107: 1
B108: 23 | C108: =IFERROR(INDEX(Regions!$A$2:$A$19,MATCH(B108,Regions!$B$2:$B$19,0))&" Workforce Center","") -> Oakmere Workforce Center | D108: 46168 | E108: 46178 | G108: 46245 | H108: N | I108: N | J108: Y | K108: 1
B109: 42 | C109: =IFERROR(INDEX(Regions!$A$2:$A$19,MATCH(B109,Regions!$B$2:$B$19,0))&" Workforce Center","") -> Willow Bend Workforce Center | D109: 46170 | E109: 46177 | F109: 46177 | G109: 46177 | H109: N | I109: N | J109: Y | K109: 1
B110: 29 | C110: =IFERROR(INDEX(Regions!$A$2:$A$19,MATCH(B110,Regions!$B$2:$B$19,0))&" Workforce Center","") -> Grand Meadow Workforce Center | D110: 46177 | E110: 46177 | F110: 46230 | G110: 46230 | H110: N | I110: N | J110: Y | K110: 1
B111: 33 | C111: =IFERROR(INDEX(Regions!$A$2:$A$19,MATCH(B111,Regions!$B$2:$B$19,0))&" Workforce Center","") -> Redstone Workforce Center | D111: 45978 | E111: 46176 | F111: 46176 | G111: 46176 | H111: N | I111: N | J111: Y | K111: 1
B112: 42 | C112: =IFERROR(INDEX(Regions!$A$2:$A$19,MATCH(B112,Regions!$B$2:$B$19,0))&" Workforce Center","") -> Willow Bend Workforce Center | D112: 46150 | E112: 46175 | F112: 46175 | G112: 46175 | H112: N | I112: N | J112: Y | K112: 1
B113: 43 | C113: =IFERROR(INDEX(Regions!$A$2:$A$19,MATCH(B113,Regions!$B$2:$B$19,0))&" Workforce Center","") -> Stonefield Workforce Center | D113: 46175 | E113: 46175 | F113: 46185 | G113: 46185 | H113: N | I113: N | J113: Y | K113: 1
B114: 15 | C114: =IFERROR(INDEX(Regions!$A$2:$A$19,MATCH(B114,Regions!$B$2:$B$19,0))&" Workforce Center","") -> Maple Crossing Workforce Center | D114: 46175 | E114: 46175 | F114: 46175 | G114: 46175 | H114: N | I114: N | J114: Y | K114: 1
B115: 43 | C115: =IFERROR(INDEX(Regions!$A$2:$A$19,MATCH(B115,Regions!$B$2:$B$19,0))&" Workforce Center","") -> Stonefield Workforce Center | D115: 46175 | E115: 46175 | F115: 46189 | G115: 46189 | H115: N | I115: N | J115: Y | K115: 1
B116: 43 | C116: =IFERROR(INDEX(Regions!$A$2:$A$19,MATCH(B116,Regions!$B$2:$B$19,0))&" Workforce Center","") -> Stonefield Workforce Center | D116: 46175 | E116: 46175 | F116: 46175 | G116: 46175 | H116: N | I116: N | J116: Y | K116: 1
B117: 48 | C117: =IFERROR(INDEX(Regions!$A$2:$A$19,MATCH(B117,Regions!$B$2:$B$19,0))&" Workforce Center","") -> Westhaven Workforce Center | D117: 46174 | E117: 46174 | F117: 46220 | G117: 46220 | H117: N | I117: N | J117: Y | K117: 1
B118: 29 | C118: =IFERROR(INDEX(Regions!$A$2:$A$19,MATCH(B118,Regions!$B$2:$B$19,0))&" Workforce Center","") -> Grand Meadow Workforce Center | D118: 46169 | E118: 46174 | F118: 46206 | G118: 46206 | H118: Y | I118: N | J118: Y | K118: 1
B119: 42 | C119: =IFERROR(INDEX(Regions!$A$2:$A$19,MATCH(B119,Regions!$B$2:$B$19,0))&" Workforce Center","") -> Willow Bend Workforce Center | D119: 46153 | E119: 46171 | G119: 46295 | H119: N | I119: N | J119: Y | K119: 1
B120: 35 | C120: =IFERROR(INDEX(Regions!$A$2:$A$19,MATCH(B120,Regions!$B$2:$B$19,0))&" Workforce Center","") -> Elm Harbor Workforce Center | D120: 46171 | E120: 46171 | F120: 46223 | G120: 46223 | H120: N | I120: N | J120: Y | K120: 1
B121: 15 | C121: =IFERROR(INDEX(Regions!$A$2:$A$19,MATCH(B121,Regions!$B$2:$B$19,0))&" Workforce Center","") -> Maple Crossing Workforce Center | D121: 46105 | E121: 46170 | F121: 46170 | G121: 46170 | H121: N | I121: N | J121: Y | K121: 1
B122: 42 | C122: =IFERROR(INDEX(Regions!$A$2:$A$19,MATCH(B122,Regions!$B$2:$B$19,0))&" Workforce Center","") -> Willow Bend Workforce Center | D122: 46164 | E122: 46170 | F122: 46170 | G122: 46170 | H122: N | I122: N | J122: Y | K122: 1
B123: 22 | C123: =IFERROR(INDEX(Regions!$A$2:$A$19,MATCH(B123,Regions!$B$2:$B$19,0))&" Workforce Center","") -> Pine Hollow Workforce Center | D123: 46169 | E123: 46169 | F123: 46230 | G123: 46230 | H123: N | I123: N | J123: Y | K123: 1
B124: 22 | C124: =IFERROR(INDEX(Regions!$A$2:$A$19,MATCH(B124,Regions!$B$2:$B$19,0))&" Workforce Center","") -> Pine Hollow Workforce Center | D124: 46168 | E124: 46168 | F124: 46219 | G124: 46219 | H124: N | I124: N | J124: Y | K124: 1
B125: 29 | C125: =IFERROR(INDEX(Regions!$A$2:$A$19,MATCH(B125,Regions!$B$2:$B$19,0))&" Workforce Center","") -> Grand Meadow Workforce Center | D125: 46168 | E125: 46168 | F125: 46226 | G125: 46226 | H125: N | I125: N | J125: Y | K125: 1
B126: 33 | C126: =IFERROR(INDEX(Regions!$A$2:$A$19,MATCH(B126,Regions!$B$2:$B$19,0))&" Workforce Center","") -> Redstone Workforce Center | D126: 46161 | E126: 46168 | F126: 46211 | G126: 46211 | H126: N | I126: N | J126: Y | K126: 1
B127: 7 | C127: =IFERROR(INDEX(Regions!$A$2:$A$19,MATCH(B127,Regions!$B$2:$B$19,0))&" Workforce Center","") -> Prairie Glen Workforce Center | D127: 46168 | E127: 46168 | F127: 46224 | G127: 46224 | H127: N | I127: N | J127: Y | K127: 1
B128: 29 | C128: =IFERROR(INDEX(Regions!$A$2:$A$19,MATCH(B128,Regions!$B$2:$B$19,0))&" Workforce Center","") -> Grand Meadow Workforce Center | D128: 46163 | E128: 46167 | F128: 46167 | G128: 46167 | H128: N | I128: N | J128: Y | K128: 1
...

Sheet Regions
A1: REGION LWDB | B1: REGION CODE | C1: REGION SHORT ABBR
A2: Cedarhaven | B2: 1 | C2: CDH
A3: Lakebridge | B3: 12 | C3: LKB
A4: Prairie Glen | B4: 7 | C4: PRG
A5: Amberfield | B5: 8 | C5: AMF
A6: Rivermoor | B6: 20 | C6: RVM
A7: Oakmere | B7: 23 | C7: OKM
A8: Pine Hollow | B8: 22 | C8: PNH
A9: Clearfork | B9: 28 | C9: CLF
A10: Grand Meadow | B10: 29 | C10: GDM
A11: Silver Creek | B11: 32 | C11: SVC
A12: Redstone | B12: 33 | C12: RDS
A13: Elm Harbor | B13: 35 | C13: ELH
... A19: Meadowbrook | B19: 50 | C19: MDB

Sheet Targets
A1: ENROLLMENT TARGETS | B1: SUB CODE | C1: SITE | D1: REGION LWDB | E1: REGION CODE
A2: 30 | B2: CDH | C2: Cedarhaven | D2: Cedarhaven | E2: 1
A3: 40 | B3: BRL | C3: Briar Lake | D3: Briar Lake | E3: 45
A4: 40 | B4: AMF | C4: Amberfield | D4: Amberfield | E4: 8
A5: 50 | B5: CLF | C5: Clearfork | D5: Clearfork | E5: 130
A6: 50 | B6: WLB | C6: Willow Bend | D6: Willow Bend | E6: 42
A7: 50 | B7: MPC | C7: Maple Crossing | D7: Maple Crossing | E7: 15
A8: 70 | B8: STF | C8: Stonefield | D8: Stonefield | E8: 43
A9: 71 | B9: OKM | C9: Oakmere | D9: Oakmere | E9: 23
A10: 80 | B10: PNH | C10: Pine Hollow | D10: Pine Hollow | E10: 120
A11: 100 | B11: RVM | C11: Rivermoor | D11: Rivermoor | E11: 110
A12: 100 | B12: PRG | C12: Prairie Glen | D12: Prairie Glen | E12: 7
A13: 100 | B13: SVC | C13: Silver Creek | D13: Silver Creek | E13: 32
... A18: 150 | B18: RDS | C18: Redstone | D18: Redstone | E18: 140

Sheet Services
A1: OFFICE | B1: SERVICE | C1: COMPLETION STATUS | D1: PROGRAM | E1: PROVIDER | F1: CREATE DATE | G1: ACTUAL BEGIN DATE | H1: PROJECTED BEGIN DATE | I1: ACTUAL END DATE | J1: PROJECTED END DATE | K1: REGISTERED APPRENTICESHIP | L1: HISPANIC | M1: COMMENTS | N1: USER ID | O1: OFFICE OF RESPONSIBILITY | P1: NAICS | Q1: ONET | R1: TYPE OF APPRENTICESHIP | S1: REGION LWDB | T1: MOST RECENT EMPLOYMENT DATE | U1: LEARNING MODE | V1: AGENCY CODE | W1: SERVICE PROVIDED | X1: EX OFFENDER | Y1: SERVICE PREFIX | Z1: SERVICE CATEGORY | AA1: CATEGORY SORT | AB1: REGION CODE
A2: Pine Hollow Workforce Center | B2: 115 - Resume Preparation Assistance | C2: Successful Completion | D2: Adult/Dislocated Worker Core, Intensive and Follow-up Office Services | E2: PNH Workforce | F2: 46244 | G2: 46219 | H2: 46219 | I2: 46219 | J2: 46219 | K2: Not Disclose | L2: No | N2: 1 | O2: Pine Hollow Workforce Center | S2: Pine Hollow | U2: No Virtual/Online, In-person Only | V2: D50 | W2: BASIC | X2: No | Y2: 115 | Z2: Basic Career Service (Staff-Assisted) | AA2: 30 | AB2: 22
A3: Pine Hollow Workforce Center | B3: 125 - Job Search and Placement Assistance | C3: Successful Completion | D3: Adult/Dislocated Worker Core, Intensive and Follow-up Office Services | E3: PNH Workforce | F3: 46244 | G3: 46226 | H3: 46226 | I3: 46226 | J3: 46226 | K3: Not Disclose | L3: No | N3: 1 | O3: Pine Hollow Workforce Center | S3: Pine Hollow | U3: No Virtual/Online, In-person Only | V3: D50 | W3: BASIC | X3: No | Y3: 125 | Z3: Basic Career Service (Staff-Assisted) | AA3: 30 | AB3: 22
A4: Pine Hollow Workforce Center | B4: 200 - Individual Counseling | C4: Successful Completion | D4: Other Office Services (Adult/Dislocated Worker) | E4: PNH Workforce | F4: 46244 | G4: 46224 | H4: 46224 | I4: 46224 | J4: 46224 | K4: Not Disclose | L4: No | N4: 1 | O4: Pine Hollow Workforce Center | S4: Pine Hollow | U4: No Virtual/Online, In-person Only | V4: D50 | W4: INDIVIDUAL SERVICES | X4: No | Y4: 200 | Z4: Individualized Career Service | AA4: 40 | AB4: 22
A5: Pine Hollow Workforce Center | B5: 125 - Job Search and Placement Assistance | C5: Successful Completion | D5: Adult/Dislocated Worker Core, Intensive and Follow-up Office Services | E5: PNH Workforce | F5: 46244 | G5: 46234 | H5: 46234 | I5: 46234 | J5: 46234 | K5: Not Disclose | L5: No | N5: 1 | O5: Pine Hollow Workforce Center | S5: Pine Hollow | U5: No Virtual/Online, In-person Only | V5: D50 | W5: BASIC | X5: No | Y5: 125 | Z5: Basic Career Service (Staff-Assisted) | AA5: 30 | AB5: 22
A6: Pine Hollow Workforce Center | B6: 189 - Supportive Service: Housing Assistance | C6: Successful Completion | D6: SS - Shelter | E6: PNH Workforce | F6: 46244 | G6: 46224 | H6: 46224 | I6: 46224 | J6: 46224 | K6: Not Disclose | L6: No | N6: 1 | O6: Pine Hollow Workforce Center | S6: Pine Hollow | U6: No Virtual/Online, In-person Only | V6: D50 | W6: 189 - Supportive Service: Housing Assistance | X6: No | Y6: 189 | Z6: Supportive Service | AA6: 70 | AB6: 22
A7: Grand Meadow Workforce Center | B7: 200 - Individual Counseling | C7: Successful Completion | D7: Individualized Career Services (Adult/DW) | E7: GDM Workforce | F7: 46241 | G7: 46231 | H7: 46231 | I7: 46231 | J7: 46231 | K7: Not Disclose | L7: No | N7: 1 | O7: Grand Meadow Workforce Center | S7: Grand Meadow | U7: No Virtual/Online, In-person Only | V7: 129 | W7: INDIVIDUAL SERVICES | X7: No | Y7: 200 | Z7: Individualized Career Service | AA7: 40 | AB7: 29
A8: Westhaven Workforce Center | B8: 101 - Orientation | C8: Successful Completion | E8: WST Workforce | F8: 46238 | G8: 46223 | I8: 46223 | J8: 46223 | K8: Not Disclose | L8: No | N8: 1 | O8: Westhaven Workforce Center | S8: Westhaven | U8: No Virtual/Online, In-person Only | V8: MCS | W8: BASIC | X8: No | Y8: 101 | Z8: Basic Career Service (Self-Service) | AA8: 20 | AB8: 48
A9: Westhaven Workforce Center | B9: 108 - Referred to WIOA Services (not training) | C9: Successful Completion | E9: WST Workforce | F9: 46238 | G9: 46223 | I9: 46223 | J9: 46223 | K9: Not Disclose | L9: No | N9: 1 | O9: Westhaven Workforce Center | S9: Westhaven | U9: No Virtual/Online, In-person Only | V9: MCS | W9: BASIC | X9: No | Y9: 108 | Z9: Basic Career Service (Staff-Assisted) | AA9: 30 | AB9: 48
A10: Silver Creek Workforce Center | B10: 112 - Job Fair | C10: Successful Completion | D10: Local Program | E10: SVC Workforce | F10: 46237 | G10: 46219 | H10: 46219 | I10: 46219 | J10: 46219 | K10: Not Disclose | L10: Yes | N10: 1 | O10: Silver Creek Workforce Center | S10: Silver Creek | U10: No Virtual/Online, In-person Only | V10: C01 | W10: BASIC | X10: No | Y10: 112 | Z10: Basic Career Service (Self-Service) | AA10: 20 | AB10: 32
A11: Pine Hollow Workforce Center | B11: 140 - Referred to Other Federal/State Assistance | C11: Successful Completion | D11: Adult/Dislocated Worker Core, Intensive and Follow-up Office Services | E11: PNH Workforce | F11: 46234 | G11: 46226 | H11: 46226 | I11: 46226 | J11: 46226 | K11: Not Disclose | L11: No | N11: 1 | O11: Pine Hollow Workforce Center | S11: Pine Hollow | U11: No Virtual/Online, In-person Only | V11: D60 | W11: 140 - Referred to Other Federal/State Assistance | X11: No | Y11: 140 | Z11: Basic Career Service (Staff-Assisted) | AA11: 30 | AB11: 22
A12: Pine Hollow Workforce Center | B12: 108 - Referred to WIOA Services (not training) | C12: Successful Completion | D12: Adult/Dislocated Worker Core, Intensive and Follow-up Office Services | E12: PNH Workforce | F12: 46234 | G12: 46226 | H12: 46226 | I12: 46226 | J12: 46226 | K12: Not Disclose | L12: No | N12: 1 | O12: Pine Hollow Workforce Center | S12: Pine Hollow | U12: No Virtual/Online, In-person Only | V12: D60 | W12: BASIC | X12: No | Y12: 108 | Z12: Basic Career Service (Staff-Assisted) | AA12: 30 | AB12: 22
A13: Pine Hollow Workforce Center | B13: 102 - Initial Assessment | C13: Successful Completion | D13: Adult/Dislocated Worker Core, Intensive and Follow-up Office Services | E13: PNH Workforce | F13: 46234 | G13: 46226 | H13: 46226 | I13: 46226 | J13: 46226 | K13: Not Disclose | L13: No | N13: 1 | O13: Pine Hollow Workforce Center | S13: Pine Hollow | U13: No Virtual/Online, In-person Only | V13: D60 | W13: BASIC | X13: No | Y13: 102 | Z13: Basic Career Service (Staff-Assisted) | AA13: 30 | AB13: 22
A14: Pine Hollow Workforce Center | B14: 101 - Orientation | C14: Successful Completion | D14: Adult/Dislocated Worker Core, Intensive and Follow-up Office Services | E14: PNH Workforce | F14: 46234 | G14: 46226 | H14: 46226 | I14: 46226 | J14: 46226 | K14: Not Disclose | L14: No | N14: 1 | O14: Pine Hollow Workforce Center | S14: Pine Hollow | U14: No Virtual/Online, In-person Only | V14: D60 | W14: BASIC | X14: No | Y14: 101 | Z14: Basic Career Service (Self-Service) | AA14: 20 | AB14: 22
A15: Silver Creek Workforce Center | B15: 202 - Career Guidance/Planning | C15: Successful Completion | D15: Local Program | E15: SVC Workforce | F15: 46234 | G15: 46230 | H15: 46230 | I15: 46230 | J15: 46230 | K15: Not Disclose | L15: No | N15: 1 | O15: Silver Creek Workforce Center | S15: Silver Creek | U15: No Virtual/Online, In-person Only | V15: C01 | W15: INDIVIDUAL SERVICES | X15: No | Y15: 202 | Z15: Individualized Career Service | AA15: 40 | AB15: 32
A16: Grand Meadow Workforce Center | B16: 102 - Initial Assessment | C16: Successful Completion | D16: Basic Career Services (Adult/DW) | E16: GDM Workforce | F16: 46234 | G16: 46233 | H16: 46233 | I16: 46233 | J16: 46233 | K16: Not Disclose | L16: Information Not Provided | N16: 1 | O16: Grand Meadow Workforce Center | S16: Grand Meadow | U16: No Virtual/Online, In-person Only | V16: 129 | W16: BASIC | X16: No | Y16: 102 | Z16: Basic Career Service (Staff-Assisted) | AA16: 30 | AB16: 29
A17: Lakebridge Workforce Center | B17: 200 - Individual Counseling | C17: Successful Completion | E17: LKB Workforce | F17: 46233 | G17: 46233 | I17: 46233 | J17: 46233 | K17: Not Disclose | L17: No | N17: 1 | O17: Lakebridge Workforce Center | S17: Lakebridge | U17: No Virtual/Online, In-person Only | W17: INDIVIDUAL SERVICES | X17: No | Y17: 200 | Z17: Individualized Career Service | AA17: 40 | AB17: 12
A18: Prairie Glen Workforce Center | B18: 200 - Individual Counseling | C18: Successful Completion | D18: Other Office Services | E18: PRG Workforce | F18: 46233 | G18: 46233 | I18: 46233 | J18: 46233 | K18: Not Disclose | L18: No | N18: 1 | O18: Prairie Glen Workforce Center | S18: Prairie Glen | T18: 46209 | U18: No Virtual/Online, In-person Only | V18: GSC1 | W18: INDIVIDUAL SERVICES | X18: No | Y18: 200 | Z18: Individualized Career Service | AA18: 40 | AB18: 7
A19: Lakebridge Workforce Center | B19: 185 - Supportive Service: Other | C19: Successful Completion | E19: LKB Workforce | F19: 46233 | G19: 46233 | I19: 46233 | J19: 46233 | K19: Not Disclose | L19: No | N19: 1 | O19: Lakebridge Workforce Center | S19: Lakebridge | U19: No Virtual/Online, In-person Only | W19: INDIVIDUAL SERVICES | X19: No | Y19: 185 | Z19: Supportive Service | AA19: 70 | AB19: 12
A20: Prairie Glen Workforce Center | B20: 185 - Supportive Service: Other | C20: Successful Completion | D20: Supportive Service - Other | E20: PRG Workforce | F20: 46233 | G20: 46233 | I20: 46233 | J20: 46233 | K20: Not Disclose | L20: No | N20: 1 | O20: Prairie Glen Workforce Center | S20: Prairie Glen | T20: 46209 | U20: No Virtual/Online, In-person Only | V20: GSC1 | W20: INDIVIDUAL SERVICES | X20: No | Y20: 185 | Z20: Supportive Service | AA20: 70 | AB20: 7
A21: Westhaven Workforce Center | B21: 202 - Career Guidance/Planning | C21: Successful Completion | E21: WST Workforce | F21: 46232 | G21: 46220 | I21: 46220 | J21: 46220 | K21: Not Disclose | L21: No | N21: 1 | O21: Westhaven Workforce Center | S21: Westhaven | U21: No Virtual/Online, In-person Only | V21: MCS | W21: INDIVIDUAL SERVICES | X21: Yes | Y21: 202 | Z21: Individualized Career Service | AA21: 40 | AB21: 48
A22: Westhaven Workforce Center | B22: 202 - Career Guidance/Planning | C22: Successful Completion | E22: WST Workforce | F22: 46232 | G22: 46220 | I22: 46220 | J22: 46220 | K22: Not Disclose | L22: Yes | N22: 1 | O22: Westhaven Workforce Center | S22: Westhaven | U22: Virtual/Online (Yes) | V22: MCS | W22: INDIVIDUAL SERVICES | X22: No | Y22: 202 | Z22: Individualized Career Service | AA22: 40 | AB22: 48
A23: Grand Meadow Workforce Center | B23: 200 - Individual Counseling | C23: Successful Completion | D23: Individualized Career Services (Adult/DW) | E23: GDM Workforce | F23: 46232 | G23: 46232 | H23: 46232 | I23: 46232 | J23: 46232 | K23: Not Disclose | L23: No | N23: 1 | O23: Grand Meadow Workforce Center | S23: Grand Meadow | T23: 46219 | U23: No Virtual/Online, In-person Only | V23: 129 | W23: INDIVIDUAL SERVICES | X23: No | Y23: 200 | Z23: Individualized Career Service | AA23: 40 | AB23: 29
A24: Westhaven Workforce Center | B24: 202 - Career Guidance/Planning | C24: Successful Completion | E24: WST Workforce | F24: 46232 | G24: 46220 | I24: 46220 | J24: 46220 | K24: Not Disclose | L24: Yes | N24: 3 | O24: Westhaven Workforce Center | S24: Westhaven | U24: No Virtual/Online, In-person Only | V24: MCS | W24: INDIVIDUAL SERVICES | X24: No | Y24: 202 | Z24: Individualized Career Service | AA24: 40 | AB24: 48
A25: Westhaven Workforce Center | B25: 202 - Career Guidance/Planning | C25: Successful Completion | E25: WST Workforce | F25: 46232 | G25: 46220 | I25: 46220 | J25: 46220 | K25: Not Disclose | L25: Yes | N25: 1 | O25: Westhaven Workforce Center | S25: Westhaven | U25: No Virtual/Online, In-person Only | V25: MCS | W25: INDIVIDUAL SERVICES | X25: Yes | Y25: 202 | Z25: Individualized Career Service | AA25: 40 | AB25: 48
A26: Grand Meadow Workforce Center | B26: 200 - Individual Counseling | C26: Successful Completion | D26: Individualized Career Services (Adult/DW) | E26: GDM Workforce | F26: 46232 | G26: 46232 | H26: 46232 | I26: 46232 | J26: 46232 | K26: Not Disclose | L26: Information Not Provided | N26: 1 | O26: Grand Meadow Workforce Center | S26: Grand Meadow | U26: No Virtual/Online, In-person Only | V26: 129 | W26: INDIVIDUAL SERVICES | X26: No | Y26: 200 | Z26: Individualized Career Service | AA26: 40 | AB26: 29
A27: Westhaven Workforce Center | B27: 202 - Career Guidance/Planning | C27: Successful Completion | E27: WST Workforce | F27: 46232 | G27: 46220 | I27: 46220 | J27: 46220 | K27: Not Disclose | L27: Information Not Provided | N27: 2 | O27: Westhaven Workforce Center | S27: Westhaven | U27: Virtual/Online (Yes) | V27: MCS | W27: INDIVIDUAL SERVICES | X27: No | Y27: 202 | Z27: Individualized Career Service | AA27: 40 | AB27: 48
A28: Westhaven Workforce Center | B28: 202 - Career Guidance/Planning | C28: Successful Completion | E28: WST Workforce | F28: 46232 | G28: 46220 | I28: 46220 | J28: 46220 | K28: Not Disclose | L28: No | N28: 2 | O28: Westhaven Workforce Center | S28: Westhaven | U28: Virtual/Online (Yes) | V28: MCS | W28: INDIVIDUAL SERVICES | X28: No | Y28: 202 | Z28: Individualized Career Service | AA28: 40 | AB28: 48
A29: Westhaven Workforce Center | B29: 202 - Career Guidance/Planning | C29: Successful Completion | E29: WST Workforce | F29: 46232 | G29: 46220 | I29: 46220 | J29: 46220 | K29: Not Disclose | L29: Yes | N29: 2 | O29: Westhaven Workforce Center | S29: Westhaven | U29: Virtual/Online (Yes) | V29: MCS | W29: INDIVIDUAL SERVICES | X29: Yes | Y29: 202 | Z29: Individualized Career Service | AA29: 40 | AB29: 48
A30: Pine Hollow Workforce Center | B30: 108 - Referred to WIOA Services (not training) | C30: Successful Completion | D30: Adult/Dislocated Worker Core, Intensive and Follow-up Office Services | E30: PNH Workforce | F30: 46231 | G30: 46216 | H30: 46216 | I30: 46216 | J30: 46216 | K30: Not Disclose | L30: No | N30: 1 | O30: Pine Hollow Workforce Center | S30: Pine Hollow | U30: No Virtual/Online, In-person Only | V30: D10 | W30: BASIC | X30: No | Y30: 108 | Z30: Basic Career Service (Staff-Assisted) | AA30: 30 | AB30: 22
A31: Westhaven Workforce Center | B31: 202 - Career Guidance/Planning | C31: Successful Completion | E31: WST Workforce | F31: 46231 | G31: 46220 | I31: 46220 | J31: 46220 | K31: Not Disclose | L31: Yes | N31: 1 | O31: Westhaven Workforce Center | S31: Westhaven | U31: Virtual/Online (Yes) | V31: MCS | W31: INDIVIDUAL SERVICES | X31: No | Y31: 202 | Z31: Individualized Career Service | AA31: 40 | AB31: 48
A32: Pine Hollow Workforce Center | B32: 102 - Initial Assessment | C32: Successful Completion | D32: Adult/Dislocated Worker Core, Intensive and Follow-up Office Services | E32: PNH Workforce | F32: 46231 | G32: 46216 | H32: 46216 | I32: 46216 | J32: 46216 | K32: Not Disclose | L32: No | N32: 1 | O32: Pine Hollow Workforce Center | S32: Pine Hollow | U32: No Virtual/Online, In-person Only | V32: D10 | W32: BASIC | X32: No | Y32: 102 | Z32: Basic Career Service (Staff-Assisted) | AA32: 30 | AB32: 22
A33: Grand Meadow Workforce Center | B33: 200 - Individual Counseling | C33: Successful Completion | D33: Individualized Career Services (Adult/DW) | E33: GDM Workforce | F33: 46231 | G33: 46231 | H33: 46231 | I33: 46231 | J33: 46231 | K33: Not Disclose | L33: No | N33: 1 | O33: Grand Meadow Workforce Center | S33: Grand Meadow | U33: No Virtual/Online, In-person Only | V33: 129 | W33: INDIVIDUAL SERVICES | X33: No | Y33: 200 | Z33: Individualized Career Service | AA33: 40 | AB33: 29
A34: Grand Meadow Workforce Center | B34: 200 - Individual Counseling | C34: Successful Completion | D34: Individualized Career Services (Adult/DW) | E34: GDM Workforce | F34: 46231 | G34: 46230 | H34: 46230 | I34: 46230 | J34: 46230 | K34: Not Disclose | L34: No | N34: 1 | O34: Grand Meadow Workforce Center | S34: Grand Meadow | U34: No Virtual/Online, In-person Only | V34: 129 | W34: INDIVIDUAL SERVICES | X34: No | Y34: 200 | Z34: Individualized Career Service | AA34: 40 | AB34: 29
A35: Westhaven Workforce Center | B35: 202 - Career Guidance/Planning | C35: Successful Completion | E35: WST Workforce | F35: 46231 | G35: 46220 | I35: 46220 | J35: 46220 | K35: Not Disclose | L35: Yes | N35: 2 | O35: Westhaven Workforce Center | S35: Westhaven | U35: Virtual/Online (Yes) | V35: MCS | W35: INDIVIDUAL SERVICES | X35: Yes | Y35: 202 | Z35: Individualized Career Service | AA35: 40 | AB35: 48
A36: Pine Hollow Workforce Center | B36: 140 - Referred to Other Federal/State Assistance | C36: Successful Completion | D36: Adult/Dislocated Worker Core, Intensive and Follow-up Office Services | E36: PNH Workforce | F36: 46231 | G36: 46216 | H36: 46216 | I36: 46216 | J36: 46216 | K36: Not Disclose | L36: No | N36: 1 | O36: Pine Hollow Workforce Center | S36: Pine Hollow | U36: No Virtual/Online, In-person Only | V36: D10 | W36: 140 - Referred to Other Federal/State Assistance | X36: No | Y36: 140 | Z36: Basic Career Service (Staff-Assisted) | AA36: 30 | AB36: 22
A37: Prairie Glen Workforce Center | B37: 125 - Job Search and Placement Assistance | C37: Successful Completion | D37: Local Office Services | E37: PRG Workforce | F37: 46231 | G37: 46231 | H37: 46231 | I37: 46231 | J37: 46231 | K37: Not Disclose | L37: Yes | N37: 1 | O37: Prairie Glen Workforce Center | S37: Prairie Glen | U37: No Virtual/Online, In-person Only | V37: GSC1 | W37: BASIC | X37: No | Y37: 125 | Z37: Basic Career Service (Staff-Assisted) | AA37: 30 | AB37: 7
A38: Pine Hollow Workforce Center | B38: 115 - Resume Preparation Assistance | C38: Successful Completion | D38: Adult/Dislocated Worker Core, Intensive and Follow-up Office Services | E38: PNH Workforce | F38: 46231 | G38: 46230 | H38: 46230 | I38: 46230 | J38: 46230 | K38: Not Disclose | L38: No | N38: 1 | O38: Pine Hollow Workforce Center | S38: Pine Hollow | U38: No Virtual/Online, In-person Only | V38: D10 | W38: BASIC | X38: No | Y38: 115 | Z38: Basic Career Service (Staff-Assisted) | AA38: 30 | AB38: 22
A39: Westhaven Workforce Center | B39: 202 - Career Guidance/Planning | C39: Successful Completion | E39: WST Workforce | F39: 46231 | G39: 46220 | I39: 46220 | J39: 46220 | K39: Not Disclose | L39: No | N39: 3 | O39: Westhaven Workforce Center | S39: Westhaven | U39: Virtual/Online (Yes) | V39: MCS | W39: INDIVIDUAL SERVICES | X39: No | Y39: 202 | Z39: Individualized Career Service | AA39: 40 | AB39: 48
A40: Pine Hollow Workforce Center | B40: 101 - Orientation | C40: Successful Completion | D40: Adult/Dislocated Worker Core, Intensive and Follow-up Office Services | E40: PNH Workforce | F40: 46231 | G40: 46216 | H40: 46216 | I40: 46216 | J40: 46216 | K40: Not Disclose | L40: No | N40: 1 | O40: Pine Hollow Workforce Center | S40: Pine Hollow | U40: No Virtual/Online, In-person Only | V40: D10 | W40: BASIC | X40: No | Y40: 101 | Z40: Basic Career Service (Self-Service) | AA40: 20 | AB40: 22
A41: Westhaven Workforce Center | B41: 202 - Career Guidance/Planning | C41: Successful Completion | E41: WST Workforce | F41: 46230 | G41: 46220 | I41: 46220 | J41: 46220 | K41: Not Disclose | L41: No | N41: 1 | O41: Westhaven Workforce Center | S41: Westhaven | U41: No Virtual/Online, In-person Only | V41: MCS | W41: INDIVIDUAL SERVICES | X41: No | Y41: 202 | Z41: Individualized Career Service | AA41: 40 | AB41: 48
A42: Westhaven Workforce Center | B42: 202 - Career Guidance/Planning | C42: Successful Completion | E42: WST Workforce | F42: 46230 | G42: 46220 | I42: 46220 | J42: 46220 | K42: Not Disclose | L42: Yes | N42: 1 | O42: Westhaven Workforce Center | S42: Westhaven | U42: Virtual/Online (Yes) | V42: MCS | W42: INDIVIDUAL SERVICES | X42: Yes | Y42: 202 | Z42: Individualized Career Service | AA42: 40 | AB42: 48
A43: Westhaven Workforce Center | B43: 202 - Career Guidance/Planning | C43: Successful Completion | E43: WST Workforce | F43: 46230 | G43: 46220 | I43: 46220 | J43: 46220 | K43: Not Disclose | L43: Yes | N43: 2 | O43: Westhaven Workforce Center | S43: Westhaven | U43: Virtual/Online (Yes) | V43: MCS | W43: INDIVIDUAL SERVICES | X43: No | Y43: 202 | Z43: Individualized Career Service | AA43: 40 | AB43: 48
A44: Prairie Glen Workforce Center | B44: 188 - Supportive Service: Tools/Clothing | C44: Successful Completion | D44: Supportive Service - Other | E44: PRG Workforce | F44: 46230 | G44: 46230 | I44: 46230 | J44: 46230 | K44: Not Disclose | L44: No | N44: 1 | O44: Prairie Glen Workforce Center | S44: Prairie Glen | U44: No Virtual/Online, In-person Only | V44: GSC1 | W44: INDIVIDUAL SERVICES | X44: Yes | Y44: 188 | Z44: Supportive Service | AA44: 70 | AB44: 7
A45: Grand Meadow Workforce Center | B45: 200 - Individual Counseling | C45: Successful Completion | D45: Individualized Career Services (Adult/DW) | E45: GDM Workforce | F45: 46230 | G45: 46230 | H45: 46230 | I45: 46230 | J45: 46230 | K45: Not Disclose | L45: No | N45: 1 | O45: Grand Meadow Workforce Center | S45: Grand Meadow | U45: No Virtual/Online, In-person Only | V45: 129 | W45: INDIVIDUAL SERVICES | X45: No | Y45: 200 | Z45: Individualized Career Service | AA45: 40 | AB45: 29
A46: Westhaven Workforce Center | B46: 202 - Career Guidance/Planning | C46: Successful Completion | E46: WST Workforce | F46: 46230 | G46: 46220 | I46: 46220 | J46: 46220 | K46: Not Disclose | L46: No | N46: 2 | O46: Westhaven Workforce Center | S46: Westhaven | U46: Virtual/Online (Yes) | V46: MCS | W46: INDIVIDUAL SERVICES | X46: No | Y46: 202 | Z46: Individualized Career Service | AA46: 40 | AB46: 48
A47: Prairie Glen Workforce Center | B47: 200 - Individual Counseling | C47: Successful Completion | D47: Other Office Services | E47: PRG Workforce | F47: 46230 | G47: 46230 | I47: 46230 | J47: 46230 | K47: Not Disclose | L47: No | N47: 1 | O47: Prairie Glen Workforce Center | S47: Prairie Glen | U47: No Virtual/Online, In-person Only | V47: GSC1 | W47: INDIVIDUAL SERVICES | X47: Yes | Y47: 200 | Z47: Individualized Career Service | AA47: 40 | AB47: 7
A48: Grand Meadow Workforce Center | B48: 200 - Individual Counseling | C48: Successful Completion | D48: Individualized Career Services (Adult/DW) | E48: GDM Workforce | F48: 46227 | G48: 46219 | H48: 46219 | I48: 46219 | J48: 46219 | K48: Not Disclose | L48: No | N48: 1 | O48: Grand Meadow Workforce Center | S48: Grand Meadow | T48: 46219 | U48: No Virtual/Online, In-person Only | V48: 129 | W48: INDIVIDUAL SERVICES | X48: No | Y48: 200 | Z48: Individualized Career Service | AA48: 40 | AB48: 29
A49: Grand Meadow Workforce Center | B49: 188 - Supportive Service: Tools/Clothing | C49: Successful Completion | D49: Support Service | E49: GDM Workforce | F49: 46227 | G49: 46219 | H49: 46219 | I49: 46219 | J49: 46219 | K49: Not Disclose | L49: No | N49: 1 | O49: Grand Meadow Workforce Center | S49: Grand Meadow | T49: 46219 | U49: No Virtual/Online, In-person Only | V49: 129 | W49: INDIVIDUAL SERVICES | X49: No | Y49: 188 | Z49: Supportive Service | AA49: 70 | AB49: 29
A50: Prairie Glen Workforce Center | B50: 181 - Supportive Service: Transportation Assistance | C50: Successful Completion | D50: Supportive Service - Transportation | E50: PRG Workforce | F50: 46227 | G50: 46227 | H50: 46227 | I50: 46227 | J50: 46227 | K50: Not Disclose | L50: No | N50: 1 | O50: Prairie Glen Workforce Center | S50: Prairie Glen | U50: No Virtual/Online, In-person Only | V50: GSC1 | W50: INDIVIDUAL SERVICES | X50: No | Y50: 181 | Z50: Supportive Service | AA50: 70 | AB50: 7
A51: Prairie Glen Workforce Center | B51: 200 - Individual Counseling | C51: Successful Completion | D51: Other Office Services | E51: PRG Workforce | F51: 46227 | G51: 46227 | H51: 46227 | I51: 46227 | J51: 46227 | K51: Not Disclose | L51: No | N51: 1 | O51: Prairie Glen Workforce Center | S51: Prairie Glen | U51: No Virtual/Online, In-person Only | V51: GSC1 | W51: INDIVIDUAL SERVICES | X51: No | Y51: 200 | Z51: Individualized Career Service | AA51: 40 | AB51: 7
A52: Redstone Workforce Center | B52: 108 - Referred to WIOA Services (not training) | C52: Successful Completion | E52: RDS Workforce | F52: 46227 | G52: 46227 | H52: 46227 | I52: 46227 | J52: 46227 | K52: Not Disclose | L52: No | N52: 1 | O52: Redstone Workforce Center | S52: Redstone | U52: No Virtual/Online, In-person Only | V52: 72 | W52: BASIC | X52: No | Y52: 108 | Z52: Basic Career Service (Staff-Assisted) | AA52: 30 | AB52: 33
A53: Grand Meadow Workforce Center | B53: 200 - Individual Counseling | C53: Successful Completion | D53: Individualized Career Services (Adult/DW) | E53: GDM Workforce | F53: 46226 | G53: 46226 | H53: 46226 | I53: 46226 | J53: 46226 | K53: Not Disclose | L53: No | N53: 1 | O53: Grand Meadow Workforce Center | S53: Grand Meadow | U53: No Virtual/Online, In-person Only | V53: 129 | W53: INDIVIDUAL SERVICES | X53: No | Y53: 200 | Z53: Individualized Career Service | AA53: 40 | AB53: 29
A54: Prairie Glen Workforce Center | B54: 205 - Development of Individual Employment Plan (IEP) | C54: Successful Completion | D54: Local Office Services | E54: PRG Workforce | F54: 46226 | G54: 46216 | H54: 46216 | I54: 46216 | J54: 46216 | K54: Not Disclose | L54: No | N54: 1 | O54: Prairie Glen Workforce Center | S54: Prairie Glen | U54: No Virtual/Online, In-person Only | V54: GSC1 | W54: INDIVIDUAL SERVICES | X54: No | Y54: 205 | Z54: Individualized Career Service | AA54: 40 | AB54: 7
A55: Westhaven Workforce Center | B55: 219 - Work Experience | E55: WST Workforce | F55: 46226 | G55: 46218 | J55: 46356 | K55: Not Disclose | L55: Yes | N55: 1 | O55: Westhaven Workforce Center | S55: Westhaven | U55: Virtual/Online (Yes) | V55: MCS | W55: 219 - Work Experience | X55: No | Y55: 219 | Z55: Individualized Career Service | AA55: 40 | AB55: 48
A56: Westhaven Workforce Center | B56: 202 - Career Guidance/Planning | C56: Successful Completion | E56: WST Workforce | F56: 46226 | G56: 46220 | I56: 46220 | J56: 46220 | K56: Not Disclose | L56: Yes | N56: 1 | O56: Westhaven Workforce Center | S56: Westhaven | U56: Virtual/Online (Yes) | V56: MCS | W56: INDIVIDUAL SERVICES | X56: No | Y56: 202 | Z56: Individualized Career Service | AA56: 40 | AB56: 48
A57: Prairie Glen Workforce Center | B57: 108 - Referred to WIOA Services (not training) | C57: Successful Completion | D57: Local Office Services | E57: PRG Workforce | F57: 46226 | G57: 46216 | H57: 46216 | I57: 46216 | J57: 46216 | K57: Not Disclose | L57: No | N57: 1 | O57: Prairie Glen Workforce Center | S57: Prairie Glen | U57: No Virtual/Online, In-person Only | V57: GSC1 | W57: BASIC | X57: No | Y57: 108 | Z57: Basic Career Service (Staff-Assisted) | AA57: 30 | AB57: 7
A58: Westhaven Workforce Center | B58: 219 - Work Experience | E58: WST Workforce | F58: 46226 | G58: 46197 | J58: 46356 | K58: Not Disclose | L58: No | N58: 1 | O58: Westhaven Workforce Center | S58: Westhaven | U58: No Virtual/Online, In-person Only | V58: MCS | W58: 219 - Work Experience | X58: Yes | Y58: 219 | Z58: Individualized Career Service | AA58: 40 | AB58: 48
A59: Prairie Glen Workforce Center | B59: 200 - Individual Counseling | C59: Successful Completion | D59: Other Office Services | E59: PRG Workforce | F59: 46226 | G59: 46216 | H59: 46216 | I59: 46216 | J59: 46216 | K59: Not Disclose | L59: No | N59: 1 | O59: Prairie Glen Workforce Center | S59: Prairie Glen | U59: No Virtual/Online, In-person Only | V59: GSC1 | W59: INDIVIDUAL SERVICES | X59: No | Y59: 200 | Z59: Individualized Career Service | AA59: 40 | AB59: 7
A60: Prairie Glen Workforce Center | B60: 102 - Initial Assessment | C60: Successful Completion | D60: Local Office Services | E60: PRG Workforce | F60: 46226 | G60: 46216 | H60: 46216 | I60: 46216 | J60: 46216 | K60: Not Disclose | L60: No | N60: 1 | O60: Prairie Glen Workforce Center | S60: Prairie Glen | U60: No Virtual/Online, In-person Only | V60: GSC1 | W60: BASIC | X60: No | Y60: 102 | Z60: Basic Career Service (Staff-Assisted) | AA60: 30 | AB60: 7
A61: Westhaven Workforce Center | B61: 202 - Career Guidance/Planning | C61: Successful Completion | E61: WST Workforce | F61: 46226 | G61: 46220 | I61: 46220 | J61: 46220 | K61: Not Disclose | L61: No | N61: 2 | O61: Westhaven Workforce Center | S61: Westhaven | U61: Virtual/Online (Yes) | V61: MCS | W61: INDIVIDUAL SERVICES | X61: No | Y61: 202 | Z61: Individualized Career Service | AA61: 40 | AB61: 48
A62: Grand Meadow Workforce Center | B62: 200 - Individual Counseling | C62: Successful Completion | D62: Individualized Career Services (Adult/DW) | E62: GDM Workforce | F62: 46225 | G62: 46225 | H62: 46225 | I62: 46225 | J62: 46225 | K62: Not Disclose | L62: No | N62: 2 | O62: Grand Meadow Workforce Center | S62: Grand Meadow | U62: No Virtual/Online, In-person Only | V62: 129 | W62: INDIVIDUAL SERVICES | X62: No | Y62: 200 | Z62: Individualized Career Service | AA62: 40 | AB62: 29
A63: Prairie Glen Workforce Center | B63: 200 - Individual Counseling | C63: Successful Completion | D63: Other Office Services | E63: PRG Workforce | F63: 46225 | G63: 46225 | I63: 46225 | J63: 46225 | K63: Not Disclose | L63: Yes | N63: 1 | O63: Prairie Glen Workforce Center | S63: Prairie Glen | T63: 46216 | U63: No Virtual/Online, In-person Only | V63: GSC1 | W63: INDIVIDUAL SERVICES | X63: Yes | Y63: 200 | Z63: Individualized Career Service | AA63: 40 | AB63: 7
A64: Westhaven Workforce Center | B64: 202 - Career Guidance/Planning | C64: Successful Completion | E64: WST Workforce | F64: 46225 | G64: 46220 | I64: 46220 | J64: 46220 | K64: Not Disclose | L64: Yes | N64: 6 | O64: Westhaven Workforce Center | S64: Westhaven | U64: Virtual/Online (Yes) | V64: MCS | W64: INDIVIDUAL SERVICES | X64: No | Y64: 202 | Z64: Individualized Career Service | AA64: 40 | AB64: 48
A65: Westhaven Workforce Center | B65: 202 - Career Guidance/Planning | C65: Successful Completion | E65: WST Workforce | F65: 46225 | G65: 46220 | I65: 46220 | J65: 46220 | K65: Not Disclose | L65: No | N65: 3 | O65: Westhaven Workforce Center | S65: Westhaven | U65: Virtual/Online (Yes) | V65: MCS | W65: INDIVIDUAL SERVICES | X65: No | Y65: 202 | Z65: Individualized Career Service | AA65: 40 | AB65: 48
A66: Westhaven Workforce Center | B66: 202 - Career Guidance/Planning | C66: Successful Completion | E66: WST Workforce | F66: 46225 | G66: 46220 | I66: 46220 | J66: 46220 | K66: Not Disclose | L66: Yes | N66: 1 | O66: Westhaven Workforce Center | S66: Westhaven | U66: No Virtual/Online, In-person Only | V66: MCS | W66: INDIVIDUAL SERVICES | X66: No | Y66: 202 | Z66: Individualized Career Service | AA66: 40 | AB66: 48
A67: Westhaven Workforce Center | B67: 202 - Career Guidance/Planning | C67: Successful Completion | E67: WST Workforce | F67: 46225 | G67: 46220 | I67: 46220 | J67: 46220 | K67: Not Disclose | L67: No | N67: 2 | O67: Westhaven Workforce Center | S67: Westhaven | U67: Virtual/Online (Yes) | V67: MCS | W67: INDIVIDUAL SERVICES | X67: Yes | Y67: 202 | Z67: Individualized Career Service | AA67: 40 | AB67: 48
A68: Westhaven Workforce Center | B68: 202 - Career Guidance/Planning | C68: Successful Completion | E68: WST Workforce | F68: 46225 | G68: 46220 | I68: 46220 | J68: 46220 | K68: Not Disclose | L68: Information Not Provided | N68: 1 | O68: Westhaven Workforce Center | S68: Westhaven | U68: Virtual/Online (Yes) | V68: MCS | W68: INDIVIDUAL SERVICES | X68: No | Y68: 202 | Z68: Individualized Career Service | AA68: 40 | AB68: 48
A69: Westhaven Workforce Center | B69: 202 - Career Guidance/Planning | C69: Successful Completion | E69: WST Workforce | F69: 46225 | G69: 46220 | I69: 46220 | J69: 46220 | K69: Not Disclose | L69: Information Not Provided | N69: 1 | O69: Westhaven Workforce Center | S69: Westhaven | U69: No Virtual/Online, In-person Only | V69: MCS | W69: INDIVIDUAL SERVICES | X69: No | Y69: 202 | Z69: Individualized Career Service | AA69: 40 | AB69: 48
A70: Westhaven Workforce Center | B70: 202 - Career Guidance/Planning | C70: Successful Completion | E70: WST Workforce | F70: 46225 | G70: 46220 | I70: 46220 | J70: 46220 | K70: Not Disclose | L70: Yes | N70: 1 | O70: Westhaven Workforce Center | S70: Westhaven | U70: Virtual/Online (Yes) | V70: MCS | W70: INDIVIDUAL SERVICES | X70: Yes | Y70: 202 | Z70: Individualized Career Service | AA70: 40 | AB70: 48
A71: Grand Meadow Workforce Center | B71: 200 - Individual Counseling | C71: Successful Completion | D71: Individualized Career Services (Adult/DW) | E71: GDM Workforce | F71: 46224 | G71: 46224 | H71: 46224 | I71: 46224 | J71: 46224 | K71: Not Disclose | L71: No | N71: 1 | O71: Grand Meadow Workforce Center | S71: Grand Meadow | U71: No Virtual/Online, In-person Only | V71: 129 | W71: INDIVIDUAL SERVICES | X71: No | Y71: 200 | Z71: Individualized Career Service | AA71: 40 | AB71: 29
A72: Pine Hollow Workforce Center | B72: 140 - Referred to Other Federal/State Assistance | C72: Successful Completion | D72: Adult/Dislocated Worker Core, Intensive and Follow-up Office Services | E72: PNH Workforce | F72: 46224 | G72: 46195 | H72: 46195 | I72: 46195 | J72: 46195 | K72: Not Disclose | L72: No | N72: 1 | O72: Pine Hollow Workforce Center | S72: Pine Hollow | T72: 46208 | U72: No Virtual/Online, In-person Only | V72: D10 | W72: 140 - Referred to Other Federal/State Assistance | X72: No | Y72: 140 | Z72: Basic Career Service (Staff-Assisted) | AA72: 30 | AB72: 22
A73: Pine Hollow Workforce Center | B73: 108 - Referred to WIOA Services (not training) | C73: Successful Completion | D73: Adult/Dislocated Worker Core, Intensive and Follow-up Office Services | E73: PNH Workforce | F73: 46224 | G73: 46195 | H73: 46195 | I73: 46195 | J73: 46195 | K73: Not Disclose | L73: No | N73: 1 | O73: Pine Hollow Workforce Center | S73: Pine Hollow | T73: 46208 | U73: No Virtual/Online, In-person Only | V73: D10 | W73: BASIC | X73: No | Y73: 108 | Z73: Basic Career Service (Staff-Assisted) | AA73: 30 | AB73: 22
A74: Pine Hollow Workforce Center | B74: 140 - Referred to Other Federal/State Assistance | C74: Successful Completion | D74: Adult/Dislocated Worker Core, Intensive and Follow-up Office Services | E74: PNH Workforce | F74: 46224 | G74: 46204 | H74: 46204 | I74: 46204 | J74: 46204 | K74: Not Disclose | L74: No | N74: 1 | O74: Pine Hollow Workforce Center | S74: Pine Hollow | U74: No Virtual/Online, In-person Only | V74: D10 | W74: 140 - Referred to Other Federal/State Assistance | X74: No | Y74: 140 | Z74: Basic Career Service (Staff-Assisted) | AA74: 30 | AB74: 22
A75: Prairie Glen Workforce Center | B75: 200 - Individual Counseling | C75: Successful Completion | D75: Other Office Services | E75: PRG Workforce | F75: 46224 | G75: 46224 | H75: 46224 | I75: 46224 | J75: 46224 | K75: Not Disclose | L75: No | N75: 1 | O75: Prairie Glen Workforce Center | S75: Prairie Glen | U75: No Virtual/Online, In-person Only | V75: GSC2 | W75: INDIVIDUAL SERVICES | X75: Yes | Y75: 200 | Z75: Individualized Career Service | AA75: 40 | AB75: 7
A76: Pine Hollow Workforce Center | B76: 140 - Referred to Other Federal/State Assistance | C76: Successful Completion | D76: Adult/Dislocated Worker Core, Intensive and Follow-up Office Services | E76: PNH Workforce | F76: 46224 | G76: 46217 | H76: 46217 | I76: 46217 | J76: 46217 | K76: Not Disclose | L76: No | N76: 1 | O76: Pine Hollow Workforce Center | S76: Pine Hollow | U76: No Virtual/Online, In-person Only | V76: D10 | W76: 140 - Referred to Other Federal/State Assistance | X76: No | Y76: 140 | Z76: Basic Career Service (Staff-Assisted) | AA76: 30 | AB76: 22
A77: Prairie Glen Workforce Center | B77: 200 - Individual Counseling | C77: Successful Completion | D77: Other Office Services | E77: PRG Workforce | F77: 46224 | G77: 46224 | I77: 46224 | J77: 46224 | K77: Not Disclose | L77: Yes | N77: 1 | O77: Prairie Glen Workforce Center | S77: Prairie Glen | U77: No Virtual/Online, In-person Only | V77: GSC1 | W77: INDIVIDUAL SERVICES | X77: No | Y77: 200 | Z77: Individualized Career Service | AA77: 40 | AB77: 7
A78: Pine Hollow Workforce Center | B78: 108 - Referred to WIOA Services (not training) | C78: Successful Completion | D78: Adult/Dislocated Worker Core, Intensive and Follow-up Office Services | E78: PNH Workforce | F78: 46224 | G78: 46217 | H78: 46217 | I78: 46217 | J78: 46217 | K78: Not Disclose | L78: No | N78: 1 | O78: Pine Hollow Workforce Center | S78: Pine Hollow | U78: No Virtual/Online, In-person Only | V78: D10 | W78: BASIC | X78: No | Y78: 108 | Z78: Basic Career Service (Staff-Assisted) | AA78: 30 | AB78: 22
A79: Pine Hollow Workforce Center | B79: 115 - Resume Preparation Assistance | C79: Successful Completion | D79: Adult/Dislocated Worker Core, Intensive and Follow-up Office Services | E79: PNH Workforce | F79: 46224 | G79: 46217 | H79: 46217 | I79: 46217 | J79: 46217 | K79: Not Disclose | L79: No | N79: 1 | O79: Pine Hollow Workforce Center | S79: Pine Hollow | U79: No Virtual/Online, In-person Only | V79: D10 | W79: BASIC | X79: No | Y79: 115 | Z79: Basic Career Service (Staff-Assisted) | AA79: 30 | AB79: 22
A80: Pine Hollow Workforce Center | B80: 108 - Referred to WIOA Services (not training) | C80: Successful Completion | D80: Adult/Dislocated Worker Core, Intensive and Follow-up Office Services | E80: PNH Workforce | F80: 46224 | G80: 46204 | H80: 46204 | I80: 46204 | J80: 46204 | K80: Not Disclose | L80: No | N80: 1 | O80: Pine Hollow Workforce Center | S80: Pine Hollow | U80: No Virtual/Online, In-person Only | V80: D10 | W80: BASIC | X80: No | Y80: 108 | Z80: Basic Career Service (Staff-Assisted) | AA80: 30 | AB80: 22
A81: Prairie Glen Workforce Center | B81: 125 - Job Search and Placement Assistance | C81: Successful Completion | D81: Local Office Services | E81: PRG Workforce | F81: 46224 | G81: 46224 | I81: 46224 | J81: 46224 | K81: Not Disclose | L81: No | N81: 1 | O81: Prairie Glen Workforce Center | S81: Prairie Glen | U81: No Virtual/Online, In-person Only | V81: GSC1 | W81: BASIC | X81: No | Y81: 125 | Z81: Basic Career Service (Staff-Assisted) | AA81: 30 | AB81: 7
A82: Pine Hollow Workforce Center | B82: 108 - Referred to WIOA Services (not training) | C82: Successful Completion | D82: Adult/Dislocated Worker Core, Intensive and Follow-up Office Services | E82: PNH Workforce | F82: 46224 | G82: 46195 | H82: 46195 | I82: 46195 | J82: 46195 | K82: Not Disclose | L82: No | N82: 2 | O82: Pine Hollow Workforce Center | S82: Pine Hollow | U82: No Virtual/Online, In-person Only | V82: D10 | W82: BASIC | X82: No | Y82: 108 | Z82: Basic Career Service (Staff-Assisted) | AA82: 30 | AB82: 22
A83: Pine Hollow Workforce Center | B83: 140 - Referred to Other Federal/State Assistance | C83: Successful Completion | D83: Adult/Dislocated Worker Core, Intensive and Follow-up Office Services | E83: PNH Workforce | F83: 46224 | G83: 46195 | H83: 46195 | I83: 46195 | J83: 46195 | K83: Not Disclose | L83: No | N83: 2 | O83: Pine Hollow Workforce Center | S83: Pine Hollow | U83: No Virtual/Online, In-person Only | V83: D10 | W83: 140 - Referred to Other Federal/State Assistance | X83: No | Y83: 140 | Z83: Basic Career Service (Staff-Assisted) | AA83: 30 | AB83: 22
A84: Grand Meadow Workforce Center | B84: 200 - Individual Counseling | C84: Successful Completion | D84: Individualized Career Services (Adult/DW) | E84: GDM Workforce | F84: 46220 | G84: 46220 | H84: 46220 | I84: 46220 | J84: 46220 | K84: Not Disclose | L84: No | N84: 1 | O84: Grand Meadow Workforce Center | S84: Grand Meadow | U84: No Virtual/Online, In-person Only | V84: 129 | W84: INDIVIDUAL SERVICES | X84: No | Y84: 200 | Z84: Individualized Career Service | AA84: 40 | AB84: 29
A85: Westhaven Workforce Center | B85: 200 - Individual Counseling | C85: Successful Completion | E85: WST Workforce | F85: 46220 | G85: 46220 | I85: 46220 | J85: 46220 | K85: Not Disclose | L85: Information Not Provided | N85: 1 | O85: Westhaven Workforce Center | S85: Westhaven | U85: No Virtual/Online, In-person Only | V85: MCS | W85: INDIVIDUAL SERVICES | X85: No | Y85: 200 | Z85: Individualized Career Service | AA85: 40 | AB85: 48
A86: Silver Creek Workforce Center | B86: 200 - Individual Counseling | C86: Successful Completion | D86: Other | E86: SVC Workforce | F86: 46220 | G86: 46220 | H86: 46220 | I86: 46220 | J86: 46220 | K86: Not Disclose | L86: Yes | N86: 1 | O86: Silver Creek Workforce Center | S86: Silver Creek | U86: No Virtual/Online, In-person Only | V86: C01 | W86: INDIVIDUAL SERVICES | X86: No | Y86: 200 | Z86: Individualized Career Service | AA86: 40 | AB86: 32
A87: Grand Meadow Workforce Center | B87: 200 - Individual Counseling | C87: Successful Completion | D87: Individualized Career Services (Adult/DW) | E87: GDM Workforce | F87: 46220 | G87: 46217 | H87: 46217 | I87: 46217 | J87: 46217 | K87: Not Disclose | L87: No | N87: 1 | O87: Grand Meadow Workforce Center | S87: Grand Meadow | U87: No Virtual/Online, In-person Only | V87: 129 | W87: INDIVIDUAL SERVICES | X87: No | Y87: 200 | Z87: Individualized Career Service | AA87: 40 | AB87: 29
A88: Pine Hollow Workforce Center | B88: 200 - Individual Counseling | C88: Successful Completion | D88: Other Office Services (Adult/Dislocated Worker) | E88: PNH Workforce | F88: 46219 | G88: 46210 | H88: 46210 | I88: 46210 | J88: 46210 | K88: Not Disclose | L88: No | N88: 1 | O88: Pine Hollow Workforce Center | S88: Pine Hollow | U88: No Virtual/Online, In-person Only | V88: D10 | W88: INDIVIDUAL SERVICES | X88: No | Y88: 200 | Z88: Individualized Career Service | AA88: 40 | AB88: 22
A89: Pine Hollow Workforce Center | B89: 205 - Development of Individual Employment Plan (IEP) | C89: Successful Completion | D89: Adult/Dislocated Worker Core, Intensive and Follow-up Office Services | E89: PNH Workforce | F89: 46219 | G89: 46211 | H89: 46211 | I89: 46211 | J89: 46211 | K89: Not Disclose | L89: No | N89: 1 | O89: Pine Hollow Workforce Center | S89: Pine Hollow | U89: No Virtual/Online, In-person Only | V89: D50 | W89: INDIVIDUAL SERVICES | X89: No | Y89: 205 | Z89: Individualized Career Service | AA89: 40 | AB89: 22
A90: Grand Meadow Workforce Center | B90: 200 - Individual Counseling | C90: Successful Completion | D90: Individualized Career Services (Adult/DW) | E90: GDM Workforce | F90: 46219 | G90: 46218 | H90: 46218 | I90: 46218 | J90: 46218 | K90: Not Disclose | L90: No | N90: 1 | O90: Grand Meadow Workforce Center | S90: Grand Meadow | U90: No Virtual/Online, In-person Only | V90: 129 | W90: INDIVIDUAL SERVICES | X90: No | Y90: 200 | Z90: Individualized Career Service | AA90: 40 | AB90: 29
A91: Pine Hollow Workforce Center | B91: 189 - Supportive Service: Housing Assistance | C91: Successful Completion | D91: SS - Shelter | E91: PNH Workforce | F91: 46219 | G91: 46219 | H91: 46219 | I91: 46219 | J91: 46219 | K91: Not Disclose | L91: No | N91: 1 | O91: Pine Hollow Workforce Center | S91: Pine Hollow | U91: No Virtual/Online, In-person Only | V91: D10 | W91: 189 - Supportive Service: Housing Assistance | X91: No | Y91: 189 | Z91: Supportive Service | AA91: 70 | AB91: 22
A92: Pine Hollow Workforce Center | B92: 203 - Objective Assessment | C92: Successful Completion | D92: Adult/Dislocated Worker Core, Intensive and Follow-up Office Services | E92: PNH Workforce | F92: 46219 | G92: 46211 | H92: 46211 | I92: 46211 | J92: 46211 | K92: Not Disclose | L92: No | N92: 1 | O92: Pine Hollow Workforce Center | S92: Pine Hollow | U92: No Virtual/Online, In-person Only | V92: D50 | W92: INDIVIDUAL SERVICES | X92: No | Y92: 203 | Z92: Individualized Career Service | AA92: 40 | AB92: 22
A93: Grand Meadow Workforce Center | B93: 200 - Individual Counseling | C93: Successful Completion | D93: Individualized Career Services (Adult/DW) | E93: GDM Workforce | F93: 46219 | G93: 46219 | H93: 46219 | I93: 46219 | J93: 46219 | K93: Not Disclose | L93: No | N93: 1 | O93: Grand Meadow Workforce Center | S93: Grand Meadow | U93: No Virtual/Online, In-person Only | V93: 129 | W93: INDIVIDUAL SERVICES | X93: No | Y93: 200 | Z93: Individualized Career Service | AA93: 40 | AB93: 29
A94: Pine Hollow Workforce Center | B94: 101 - Orientation | C94: Successful Completion | D94: Adult/Dislocated Worker Core, Intensive and Follow-up Office Services | E94: PNH Workforce | F94: 46219 | G94: 46217 | H94: 46217 | I94: 46217 | J94: 46217 | K94: Not Disclose | L94: No | N94: 1 | O94: Pine Hollow Workforce Center | S94: Pine Hollow | U94: No Virtual/Online, In-person Only | V94: D10 | W94: BASIC | X94: No | Y94: 101 | Z94: Basic Career Service (Self-Service) | AA94: 20 | AB94: 22
A95: Prairie Glen Workforce Center | B95: 200 - Individual Counseling | C95: Successful Completion | D95: Other Office Services | E95: PRG Workforce | F95: 46219 | G95: 46219 | I95: 46219 | J95: 46219 | K95: Not Disclose | L95: No | N95: 1 | O95: Prairie Glen Workforce Center | S95: Prairie Glen | T95: 46209 | U95: No Virtual/Online, In-person Only | V95: GSC1 | W95: INDIVIDUAL SERVICES | X95: No | Y95: 200 | Z95: Individualized Career Service | AA95: 40 | AB95: 7
A96: Pine Hollow Workforce Center | B96: 102 - Initial Assessment | C96: Successful Completion | D96: Adult/Dislocated Worker Core, Intensive and Follow-up Office Services | E96: PNH Workforce | F96: 46219 | G96: 46217 | H96: 46217 | I96: 46217 | J96: 46217 | K96: Not Disclose | L96: No | N96: 1 | O96: Pine Hollow Workforce Center | S96: Pine Hollow | U96: No Virtual/Online, In-person Only | V96: D10 | W96: BASIC | X96: No | Y96: 102 | Z96: Basic Career Service (Staff-Assisted) | AA96: 30 | AB96: 22
A97: Pine Hollow Workforce Center | B97: 188 - Supportive Service: Tools/Clothing | C97: Successful Completion | D97: Supportive Services | E97: PNH Workforce | F97: 46219 | G97: 46219 | H97: 46219 | I97: 46219 | J97: 46219 | K97: Not Disclose | L97: No | N97: 1 | O97: Pine Hollow Workforce Center | S97: Pine Hollow | U97: No Virtual/Online, In-person Only | V97: D10 | W97: INDIVIDUAL SERVICES | X97: No | Y97: 188 | Z97: Supportive Service | AA97: 70 | AB97: 22
A98: Pine Hollow Workforce Center | B98: 140 - Referred to Other Federal/State Assistance | C98: Successful Completion | D98: Adult/Dislocated Worker Core, Intensive and Follow-up Office Services | E98: PNH Workforce | F98: 46218 | G98: 46191 | H98: 46191 | I98: 46191 | J98: 46191 | K98: Not Disclose | L98: No | N98: 1 | O98: Pine Hollow Workforce Center | S98: Pine Hollow | U98: No Virtual/Online, In-person Only | V98: D50 | W98: 140 - Referred to Other Federal/State Assistance | X98: No | Y98: 140 | Z98: Basic Career Service (Staff-Assisted) | AA98: 30 | AB98: 22
A99: Pine Hollow Workforce Center | B99: 102 - Initial Assessment | C99: Successful Completion | D99: Adult/Dislocated Worker Core, Intensive and Follow-up Office Services | E99: PNH Workforce | F99: 46218 | G99: 46211 | H99: 46211 | I99: 46211 | J99: 46211 | K99: Not Disclose | L99: No | N99: 1 | O99: Pine Hollow Workforce Center | S99: Pine Hollow | U99: No Virtual/Online, In-person Only | V99: D50 | W99: BASIC | X99: No | Y99: 102 | Z99: Basic Career Service (Staff-Assisted) | AA99: 30 | AB99: 22
A100: Pine Hollow Workforce Center | B100: 101 - Orientation | C100: Successful Completion | D100: Adult/Dislocated Worker Core, Intensive and Follow-up Office Services | E100: PNH Workforce | F100: 46218 | G100: 46211 | H100: 46211 | I100: 46211 | J100: 46211 | K100: Not Disclose | L100: No | N100: 1 | O100: Pine Hollow Workforce Center | S100: Pine Hollow | U100: No Virtual/Online, In-person Only | V100: D50 | W100: BASIC | X100: No | Y100: 101 | Z100: Basic Career Service (Self-Service) | AA100: 20 | AB100: 22
...
